Metadata-Version: 2.4
Name: Image_processing_testing_package
Version: 0.0.2
Summary: image processing package
Home-page: https://github.com/Le0Vieir4/image-processing-package
Author: Leonardo Vieira Moreira
Author-email: lvm9508@gmail.com
Requires-Python: >=3.8
Requires-Dist: setuptools
Requires-Dist: wheel
Requires-Dist: twine
Dynamic: author
Dynamic: author-email
Dynamic: description
Dynamic: description-content-type
Dynamic: home-page
Dynamic: requires-dist
Dynamic: requires-python
Dynamic: summary
